odoo/addons/mrp_unbuild_valuation_layer_link/README.rst
odoo/addons/mrp_unbuild_valuation_layer_link/__init__.py
odoo/addons/mrp_unbuild_valuation_layer_link/__manifest__.py
odoo/addons/mrp_unbuild_valuation_layer_link/i18n/it.po
odoo/addons/mrp_unbuild_valuation_layer_link/i18n/mrp_unbuild_valuation_layer_link.pot
odoo/addons/mrp_unbuild_valuation_layer_link/i18n/pt_BR.po
odoo/addons/mrp_unbuild_valuation_layer_link/models/__init__.py
odoo/addons/mrp_unbuild_valuation_layer_link/models/mrp_unbuild.py
odoo/addons/mrp_unbuild_valuation_layer_link/readme/CONTRIBUTORS.md
odoo/addons/mrp_unbuild_valuation_layer_link/readme/DESCRIPTION.md
odoo/addons/mrp_unbuild_valuation_layer_link/readme/USAGE.md
odoo/addons/mrp_unbuild_valuation_layer_link/static/description/icon.png
odoo/addons/mrp_unbuild_valuation_layer_link/static/description/index.html
odoo/addons/mrp_unbuild_valuation_layer_link/tests/__init__.py
odoo/addons/mrp_unbuild_valuation_layer_link/tests/test_mrp__unbuild_valuation_layer_link.py
odoo/addons/mrp_unbuild_valuation_layer_link/views/mrp_unbuild_views.xml
odoo_addon_mrp_unbuild_valuation_layer_link-18.0.1.0.0.3.dist-info/METADATA
odoo_addon_mrp_unbuild_valuation_layer_link-18.0.1.0.0.3.dist-info/WHEEL
odoo_addon_mrp_unbuild_valuation_layer_link-18.0.1.0.0.3.dist-info/top_level.txt
odoo_addon_mrp_unbuild_valuation_layer_link-18.0.1.0.0.3.dist-info/RECORD
